MANIFEST.in
README.rst
setup.py
FrAG.egg-info/PKG-INFO
FrAG.egg-info/SOURCES.txt
FrAG.egg-info/dependency_links.txt
FrAG.egg-info/requires.txt
FrAG.egg-info/top_level.txt
frag_pele/__init__.py
frag_pele/constants.py
frag_pele/log_configure.ini
frag_pele/main.py
frag_pele/serie_handler.py
frag_pele/AdaptivePELE_repo/__init__.py
frag_pele/AdaptivePELE_repo/setup.py
frag_pele/AdaptivePELE_repo/AdaptivePELE/__init__.py
frag_pele/AdaptivePELE_repo/AdaptivePELE/adaptiveSampling.py
frag_pele/AdaptivePELE_repo/AdaptivePELE/automateRoundsAdaptive.py
frag_pele/AdaptivePELE_repo/AdaptivePELE/makeRelease.py
frag_pele/AdaptivePELE_repo/AdaptivePELE/runAllTests.py
frag_pele/AdaptivePELE_repo/AdaptivePELE/analysis/__init__.py
frag_pele/AdaptivePELE_repo/AdaptivePELE/analysis/addRejectedSteps.py
frag_pele/AdaptivePELE_repo/AdaptivePELE/analysis/analyse.py
frag_pele/AdaptivePELE_repo/AdaptivePELE/analysis/analyseClustering.py
frag_pele/AdaptivePELE_repo/AdaptivePELE/analysis/backtrackAdaptiveTrajectory.py
frag_pele/AdaptivePELE_repo/AdaptivePELE/analysis/compareClustering.py
frag_pele/AdaptivePELE_repo/AdaptivePELE/analysis/correctRMSD.py
frag_pele/AdaptivePELE_repo/AdaptivePELE/analysis/findfirstbindingevent.py
frag_pele/AdaptivePELE_repo/AdaptivePELE/analysis/foldersFirstBindingEvent.py
frag_pele/AdaptivePELE_repo/AdaptivePELE/analysis/histCM.py
frag_pele/AdaptivePELE_repo/AdaptivePELE/analysis/makePNGs.py
frag_pele/AdaptivePELE_repo/AdaptivePELE/analysis/networkCM.py
frag_pele/AdaptivePELE_repo/AdaptivePELE/analysis/numberOfClusters.py
frag_pele/AdaptivePELE_repo/AdaptivePELE/analysis/pathwayRMSD.py
frag_pele/AdaptivePELE_repo/AdaptivePELE/analysis/plot3DNetwork.py
frag_pele/AdaptivePELE_repo/AdaptivePELE/analysis/plotAdaptive.py
frag_pele/AdaptivePELE_repo/AdaptivePELE/analysis/plotRMSF.py
frag_pele/AdaptivePELE_repo/AdaptivePELE/analysis/plotSpawningClusters.py
frag_pele/AdaptivePELE_repo/AdaptivePELE/analysis/splitTrajectory.py
frag_pele/AdaptivePELE_repo/AdaptivePELE/analysis/writeClusteringStructures.py
frag_pele/AdaptivePELE_repo/AdaptivePELE/analysis/writeNetworkFiles.py
